{
  "DocumentConnection": {
    "type": "DocumentConnection",
    "resolveType": "multiCollectionDocumentList",
    "collections": [
      "global",
      "modifier",
      "menu",
      "posts"
    ]
  },
  "Node": {
    "type": "Node",
    "resolveType": "nodeDocument"
  },
  "DocumentNode": {
    "type": "DocumentNode",
    "resolveType": "multiCollectionDocument",
    "createDocument": "create",
    "updateDocument": "update"
  },
  "GlobalDocument": {
    "type": "GlobalDocument",
    "resolveType": "collectionDocument",
    "collection": "global",
    "createGlobalDocument": "create",
    "updateGlobalDocument": "update"
  },
  "GlobalConnection": {
    "type": "GlobalConnection",
    "resolveType": "collectionDocumentList",
    "collection": "global"
  },
  "ModifierDocument": {
    "type": "ModifierDocument",
    "resolveType": "collectionDocument",
    "collection": "modifier",
    "createModifierDocument": "create",
    "updateModifierDocument": "update"
  },
  "ModifierConnection": {
    "type": "ModifierConnection",
    "resolveType": "collectionDocumentList",
    "collection": "modifier"
  },
  "MenuSectionItemModifierDocument": {
    "type": "MenuSectionItemModifierDocument",
    "resolveType": "multiCollectionDocument",
    "createDocument": "create",
    "updateDocument": "update"
  },
  "MenuDocument": {
    "type": "MenuDocument",
    "resolveType": "collectionDocument",
    "collection": "menu",
    "createMenuDocument": "create",
    "updateMenuDocument": "update"
  },
  "MenuConnection": {
    "type": "MenuConnection",
    "resolveType": "collectionDocumentList",
    "collection": "menu"
  },
  "PostsDocument": {
    "type": "PostsDocument",
    "resolveType": "collectionDocument",
    "collection": "posts",
    "createPostsDocument": "create",
    "updatePostsDocument": "update"
  },
  "PostsConnection": {
    "type": "PostsConnection",
    "resolveType": "collectionDocumentList",
    "collection": "posts"
  }
}